[{"word":"groggy","type":"adjective","pronunc":{"uk":{"mp3":"http://dictionary.cambridge.org/media/english/uk_pron/u/ukg/ukgri/ukgrind026.mp3","ogg":"http://dictionary.cambridge.org/media/english/uk_pron_ogg/u/ukg/ukgri/ukgrind026.ogg","text":"ˈɡrɒɡ.i"},"us":{"mp3":"http://dictionary.cambridge.org/media/english/us_pron/g/gro/grogg/groggy.mp3","ogg":"http://dictionary.cambridge.org/media/english/us_pron_ogg/g/gro/grogg/groggy.ogg","text":"ˈɡrɑː.ɡi"}},"definitions":[{"definition":"weak and unable to think clearly or walk correctly, usually because of tiredness or illness: ","examples":["I felt a little bit groggy for a couple of days after the operation."]}]}]