[{"word":"pallet","type":"noun","pronunc":{"uk":{"mp3":"http://dictionary.cambridge.org/media/english/uk_pron/u/ukp/ukpal/ukpalef014.mp3","ogg":"http://dictionary.cambridge.org/media/english/uk_pron_ogg/u/ukp/ukpal/ukpalef014.ogg","text":"ˈpæl.ɪt"},"us":{"mp3":"http://dictionary.cambridge.org/media/english/us_pron/u/usp/uspal/uspalav012.mp3","ogg":"http://dictionary.cambridge.org/media/english/us_pron_ogg/u/usp/uspal/uspalav012.ogg","text":"ˈpæl.ɪt"}},"definitions":[{"definition":"a flat wooden structure that heavy goods are put onto so that they can be moved using a fork-lift truck (= a small vehicle with two strong bars of metal on the front that is used for lifting heavy goods)"}]}]