[{"word":"paradise","type":"noun","pronunc":{"uk":{"mp3":"http://dictionary.cambridge.org/media/english/uk_pron/u/ukp/ukpap/ukpaper023.mp3","ogg":"http://dictionary.cambridge.org/media/english/uk_pron_ogg/u/ukp/ukpap/ukpaper023.ogg","text":"ˈpær.ə.daɪs"},"us":{"mp3":"http://dictionary.cambridge.org/media/english/us_pron/p/par/parad/paradise.mp3","ogg":"http://dictionary.cambridge.org/media/english/us_pron_ogg/p/par/parad/paradise.ogg","text":"ˈper.ə.daɪs"}},"definitions":[{"definition":"a place or condition of great happiness where everything is exactly as you would like it to be: ","examples":["a tropical paradise"]},{"definition":"Heaven: ","examples":["They believe they'll go to Paradise after they die."]},{"definition":"the garden of Eden (= the place where Adam and Eve lived, in the Bible story)"}]}]