[{"word":"phallus","type":"noun","pronunc":{"uk":{"mp3":"http://dictionary.cambridge.org/media/english/uk_pron/u/ukp/ukpff/ukpfft_012.mp3","ogg":"http://dictionary.cambridge.org/media/english/uk_pron_ogg/u/ukp/ukpff/ukpfft_012.ogg","text":"ˈfæl.əs"},"us":{"mp3":"http://dictionary.cambridge.org/media/english/us_pron/u/usp/uspes/uspestl030.mp3","ogg":"http://dictionary.cambridge.org/media/english/us_pron_ogg/u/usp/uspes/uspestl030.ogg","text":"ˈfæl.əs"}},"definitions":[{"definition":"an image or a model of the penis, especially one representing the power of men to make women pregnant, or a penis: ","examples":["These primitive peoples are believed to have worshipped the phallus as a symbol of regeneration."]}]}]