[{"word":"phenomenal","type":"adjective","pronunc":{"uk":{"mp3":"http://dictionary.cambridge.org/media/english/uk_pron/u/ukp/ukpff/ukpfft_028.mp3","ogg":"http://dictionary.cambridge.org/media/english/uk_pron_ogg/u/ukp/ukpff/ukpfft_028.ogg","text":"fəˈnɒm.ɪ.nə"},"us":{"mp3":"http://dictionary.cambridge.org/media/english/us_pron/p/phe/pheno/phenomenal.mp3","ogg":"http://dictionary.cambridge.org/media/english/us_pron_ogg/p/phe/pheno/phenomenal.ogg","text":"fəˈnɑː.mə.nə"}},"definitions":[{"definition":"extremely successful or special, especially in a surprising way: ","examples":["Her rise to fame was quite phenomenal - in less than two years she was a household name."]}]}]