[{"word":"pottery","type":"noun","pronunc":{"uk":{"mp3":"http://dictionary.cambridge.org/media/english/uk_pron/u/ukp/ukpos/ukpostw030.mp3","ogg":"http://dictionary.cambridge.org/media/english/uk_pron_ogg/u/ukp/ukpos/ukpostw030.ogg","text":"ˈpɒt.ə"},"us":{"mp3":"http://dictionary.cambridge.org/media/english/us_pron/p/pot/potte/pottery.mp3","ogg":"http://dictionary.cambridge.org/media/english/us_pron_ogg/p/pot/potte/pottery.ogg","text":"ˈpɑː.t̬ɚ.i"}},"definitions":[{"definition":"the activity or skill of making clay objects by hand"},{"definition":"objects that are made out of clay by hand: ","examples":["They sell pottery and other handmade goods."]}]}]