[{"word":"purity","type":"noun","pronunc":{"uk":{"mp3":"http://dictionary.cambridge.org/media/english/uk_pron/u/ukp/ukpur/ukpurit002.mp3","ogg":"http://dictionary.cambridge.org/media/english/uk_pron_ogg/u/ukp/ukpur/ukpurit002.ogg","text":"ˈpjʊə.rə.ti"},"us":{"mp3":"http://dictionary.cambridge.org/media/english/us_pron/p/pur/purit/purity.mp3","ogg":"http://dictionary.cambridge.org/media/english/us_pron_ogg/p/pur/purit/purity.ogg","text":"ˈpjʊr.ə.t̬i"}},"definitions":[{"definition":"the state of not being mixed with anything else: ","examples":["the atrocities carried out in the name of ethnic/racial purity"]},{"definition":"the clear and perfect quality of a sound: ","examples":["the purity of her voice"]},{"definition":"the fact of being clean or free from harmful substances: ","examples":["air/water purity"]}]}]