[{"word":"pyre","type":"noun","pronunc":{"uk":{"mp3":"http://dictionary.cambridge.org/media/english/uk_pron/u/ukp/ukput/ukputz_016.mp3","ogg":"http://dictionary.cambridge.org/media/english/uk_pron_ogg/u/ukp/ukput/ukputz_016.ogg","text":"paɪər"},"us":{"mp3":"http://dictionary.cambridge.org/media/english/us_pron/p/pyr/pyre_/pyre.mp3","ogg":"http://dictionary.cambridge.org/media/english/us_pron_ogg/p/pyr/pyre_/pyre.ogg","text":"paɪr"}},"definitions":[{"definition":"a large pile of wood on which a dead body is burned in some parts of the world: ","examples":["A traditional Hindu custom used to involve widows burning themselves alive on their husbands' funeral pyres."]}]}]