[{"word":"barley","type":"noun","pronunc":{"uk":{"mp3":"http://dictionary.cambridge.org/media/english/uk_pron/u/ukb/ukbar/ukbareb015.mp3","ogg":"http://dictionary.cambridge.org/media/english/uk_pron_ogg/u/ukb/ukbar/ukbareb015.ogg","text":"ˈbɑː.li"},"us":{"mp3":"http://dictionary.cambridge.org/media/english/us_pron/b/bar/barle/barley.mp3","ogg":"http://dictionary.cambridge.org/media/english/us_pron_ogg/b/bar/barle/barley.ogg","text":"ˈbɑːr.li"}},"definitions":[{"definition":"a tall plant like grass with long, straight hairs growing from the head of each stem, or the grain from this plant, used for food and for making beer and whisky"}]}]