[{"word":"beanie","type":"noun","pronunc":{"uk":{"mp3":"http://dictionary.cambridge.org/media/english/uk_pron/e/epd/epd03/epd03054.mp3","ogg":"http://dictionary.cambridge.org/media/english/uk_pron_ogg/e/epd/epd03/epd03054.ogg","text":"ˈbiː.ni"},"us":{"mp3":"http://dictionary.cambridge.org/media/english/us_pron/c/cus/cus00/cus00167.mp3","ogg":"http://dictionary.cambridge.org/media/english/us_pron_ogg/c/cus/cus00/cus00167.ogg","text":"ˈbiː.ni"}},"definitions":[{"definition":"a small hat that fits closely to the head: ","examples":["a beanie hat/cap"]},{"definition":"a hat made from wool with a small round wool ball on top","examples":[" Compare\n\t\n                bobble hat"]}]}]