[{"word":"blowhole","type":"noun","pronunc":{"uk":{"mp3":"http://dictionary.cambridge.org/media/english/uk_pron/u/ukb/ukblo/ukblowg003.mp3","ogg":"http://dictionary.cambridge.org/media/english/uk_pron_ogg/u/ukb/ukblo/ukblowg003.ogg","text":"ˈbləʊ.həʊl"},"us":{"mp3":"http://dictionary.cambridge.org/media/english/us_pron/u/usb/usblo/usblous005.mp3","ogg":"http://dictionary.cambridge.org/media/english/us_pron_ogg/u/usb/usblo/usblous005.ogg","text":"ˈbloʊ.hoʊl"}},"definitions":[{"definition":"an opening in the top of the head of a whale (= very large sea mammal), through which it breathes"},{"definition":"a hole in the ground that connects to a cave opening into the sea"}]}]