[{"word":"bolognese","type":"noun","pronunc":{"uk":{"mp3":"http://dictionary.cambridge.org/media/english/uk_pron/e/epd/epd03/epd03903.mp3","ogg":"http://dictionary.cambridge.org/media/english/uk_pron_ogg/e/epd/epd03/epd03903.ogg","text":"ˌbɒl.əˈneɪz"},"us":{"mp3":"http://dictionary.cambridge.org/media/english/us_pron/e/eus/eus70/eus70569.mp3","ogg":"http://dictionary.cambridge.org/media/english/us_pron_ogg/e/eus/eus70/eus70569.ogg","text":"ˌboʊ.ləˈniːz"}},"definitions":[{"definition":"a type of sauce made with minced meat (= meat cut up into very small pieces) and tomatoes, usually eaten with pasta: ","examples":["spaghetti bolognese"]}]}]