[{"word":"brutal","type":"adjective","pronunc":{"uk":{"mp3":"http://dictionary.cambridge.org/media/english/uk_pron/u/ukb/ukbru/ukbrusq004.mp3","ogg":"http://dictionary.cambridge.org/media/english/uk_pron_ogg/u/ukb/ukbru/ukbrusq004.ogg","text":"ˈbruː.tə"},"us":{"mp3":"http://dictionary.cambridge.org/media/english/us_pron/e/eus/eus70/eus70617.mp3","ogg":"http://dictionary.cambridge.org/media/english/us_pron_ogg/e/eus/eus70/eus70617.ogg","text":"ˈbruː.t̬ə"}},"definitions":[{"definition":"cruel, violent, and completely without feelings: ","examples":["a brutal dictator"]},{"definition":"not considering someone's feelings: ","examples":["She spoke with brutal honesty - I was too old for the job."]}]}]