[{"word":"hackneyed","type":"adjective","pronunc":{"uk":{"mp3":"http://dictionary.cambridge.org/media/english/uk_pron/u/ukg/ukgyr/ukgyros021.mp3","ogg":"http://dictionary.cambridge.org/media/english/uk_pron_ogg/u/ukg/ukgyr/ukgyros021.ogg","text":"ˈhæk.nid"},"us":{"mp3":"http://dictionary.cambridge.org/media/english/us_pron/h/hac/hackn/hackneyed.mp3","ogg":"http://dictionary.cambridge.org/media/english/us_pron_ogg/h/hac/hackn/hackneyed.ogg","text":"ˈhæk.nid"}},"definitions":[{"definition":"A hackneyed phrase or idea has been said or used so often that it has become boring and has no meaning: ","examples":["The plot of the film is just a hackneyed boy-meets-girl scenario."]}]}]