[{"word":"whippersnapper","type":"noun","pronunc":{"uk":{"mp3":"http://dictionary.cambridge.org/media/english/uk_pron/u/ukw/ukwhi/ukwhich020.mp3","ogg":"http://dictionary.cambridge.org/media/english/uk_pron_ogg/u/ukw/ukwhi/ukwhich020.ogg","text":"ˈwɪp.əˌsnæp.ər"},"us":{"mp3":"http://dictionary.cambridge.org/media/english/us_pron/u/usw/uswhe/uswheez013.mp3","ogg":"http://dictionary.cambridge.org/media/english/us_pron_ogg/u/usw/uswhe/uswheez013.ogg","text":"ˈwɪp.ɚˌsnæp.ɚ"}},"definitions":[{"definition":"a young person who is too confident and shows no respect towards other, especially older, people: ","examples":["I'm not going to have some young whippersnapper tell me what to do!"]}]}]