[{"word":"exchange","type":"noun","pronunc":{"uk":{"mp3":"http://dictionary.cambridge.org/media/english/uk_pron/u/uke/ukexc/ukexces004.mp3","ogg":"http://dictionary.cambridge.org/media/english/uk_pron_ogg/u/uke/ukexc/ukexces004.ogg","text":"ɪksˈtʃeɪndʒ"},"us":{"mp3":"http://dictionary.cambridge.org/media/english/us_pron/e/exc/excha/exchange.mp3","ogg":"http://dictionary.cambridge.org/media/english/us_pron_ogg/e/exc/excha/exchange.ogg","text":"ɪksˈtʃeɪndʒ"}},"definitions":[{"definition":"the act of giving something to someone and them giving you something else: ","examples":["an exchange of ideas/information"]}]},{"word":"exchange","type":"verb","pronunc":{"uk":{"mp3":"http://dictionary.cambridge.org/media/english/uk_pron/u/uke/ukexc/ukexces004.mp3","ogg":"http://dictionary.cambridge.org/media/english/uk_pron_ogg/u/uke/ukexc/ukexces004.ogg","text":"ɪksˈtʃeɪndʒ"},"us":{"mp3":"http://dictionary.cambridge.org/media/english/us_pron/e/exc/excha/exchange.mp3","ogg":"http://dictionary.cambridge.org/media/english/us_pron_ogg/e/exc/excha/exchange.ogg","text":"ɪksˈtʃeɪndʒ"}},"definitions":[{"definition":"to give something to someone and receive something from that person: ","examples":["It's traditional for the two teams to exchange shirts after the game."]},{"definition":"to take something back to a shop where it was bought and get something else instead: ","examples":["If you don't like the gift, you can exchange it."]}]}]