[{"word":"nostril","type":"noun","pronunc":{"uk":{"mp3":"http://dictionary.cambridge.org/media/english/uk_pron/u/ukn/uknos/uknosh_009.mp3","ogg":"http://dictionary.cambridge.org/media/english/uk_pron_ogg/u/ukn/uknos/uknosh_009.ogg","text":"ˈnɒs.trə"},"us":{"mp3":"http://dictionary.cambridge.org/media/english/us_pron/n/nos/nostr/nostril.mp3","ogg":"http://dictionary.cambridge.org/media/english/us_pron_ogg/n/nos/nostr/nostril.ogg","text":"ˈnɑː.strə"}},"definitions":[{"definition":"either of the two openings in the nose through which air moves when you breathe: ","examples":["The horses came to a halt, steam streaming from their nostrils."]}]}]