[{"word":"landfall","type":"noun","pronunc":{"uk":{"mp3":"http://dictionary.cambridge.org/media/english/uk_pron/u/ukl/uklam/uklampl012.mp3","ogg":"http://dictionary.cambridge.org/media/english/uk_pron_ogg/u/ukl/uklam/uklampl012.ogg","text":"ˈlænd.fɔːl"},"us":{"mp3":"http://dictionary.cambridge.org/media/english/us_pron/u/usl/uslai/uslaird025.mp3","ogg":"http://dictionary.cambridge.org/media/english/us_pron_ogg/u/usl/uslai/uslaird025.ogg","text":"ˈlænd.fɑːl"}},"definitions":[{"definition":"the first land that is reached or seen at the end of a journey across the sea or through the air, or the fact of arriving there: ","examples":["Shannon Airport in Ireland was the first European landfall for planes flying from North America."]}]}]