[{"word":"lynch","type":"verb","pronunc":{"uk":{"mp3":"http://dictionary.cambridge.org/media/english/uk_pron/u/ukl/uklyc/uklycee008.mp3","ogg":"http://dictionary.cambridge.org/media/english/uk_pron_ogg/u/ukl/uklyc/uklycee008.ogg","text":"lɪntʃ"},"us":{"mp3":"http://dictionary.cambridge.org/media/english/us_pron/l/lyn/lynch/lynch.mp3","ogg":"http://dictionary.cambridge.org/media/english/us_pron_ogg/l/lyn/lynch/lynch.ogg","text":"lɪntʃ"}},"definitions":[{"definition":"If a crowd of people lynch someone who they believe is guilty of a crime, they kill them without a legal trial, usually by hanging (= killing using a rope round the neck)."}]}]