[{"word":"arthritis","type":"noun","pronunc":{"uk":{"mp3":"http://dictionary.cambridge.org/media/english/uk_pron/u/uka/ukarr/ukarriv027.mp3","ogg":"http://dictionary.cambridge.org/media/english/uk_pron_ogg/u/uka/ukarr/ukarriv027.ogg","text":"ɑːˈθraɪ.tɪs"},"us":{"mp3":"http://dictionary.cambridge.org/media/english/us_pron/a/art/arthr/arthritis.mp3","ogg":"http://dictionary.cambridge.org/media/english/us_pron_ogg/a/art/arthr/arthritis.ogg","text":"ɑːrˈθraɪ.t̬əs"}},"definitions":[{"definition":"a serious condition in which a person's joints (= the places where two bones are connected) become painful, swollen, and stiff: ","examples":["In later life she was crippled with arthritis."]}]}]