[{"word":"awareness","type":"noun","pronunc":{"uk":{"mp3":"http://dictionary.cambridge.org/media/english/uk_pron/u/uka/ukavi/ukaviat026.mp3","ogg":"http://dictionary.cambridge.org/media/english/uk_pron_ogg/u/uka/ukavi/ukaviat026.ogg","text":"əˈweə.nəs"},"us":{"mp3":"http://dictionary.cambridge.org/media/english/us_pron/a/awa/aware/awareness.mp3","ogg":"http://dictionary.cambridge.org/media/english/us_pron_ogg/a/awa/aware/awareness.ogg","text":"əˈwer.nəs"}},"definitions":[{"definition":"knowledge that something exists, or understanding of a situation or subject at the present time based on information or experience: ","examples":["Public awareness of the problem will make politicians take it seriously."]}]}]