[{"word":"inpatient","type":"noun","pronunc":{"uk":{"mp3":"http://dictionary.cambridge.org/media/english/uk_pron/u/ukc/ukcld/ukcld00742.mp3","ogg":"http://dictionary.cambridge.org/media/english/uk_pron_ogg/u/ukc/ukcld/ukcld00742.ogg","text":"ˈɪn.peɪ.ʃə"},"us":{"mp3":"http://dictionary.cambridge.org/media/english/us_pron/u/usc/uscld/uscld00742.mp3","ogg":"http://dictionary.cambridge.org/media/english/us_pron_ogg/u/usc/uscld/uscld00742.ogg","text":"ˈɪn.peɪ.ʃə"}},"definitions":[{"definition":"a person who goes into hospital to receive medical care, and stays there one or more nights while they are being treated","examples":[" Compare\n\t\n                outpatient"]}]}]