[{"word":"isolate","type":"verb","pronunc":{"uk":{"mp3":"http://dictionary.cambridge.org/media/english/uk_pron/u/uki/ukiso/ukisola001.mp3","ogg":"http://dictionary.cambridge.org/media/english/uk_pron_ogg/u/uki/ukiso/ukisola001.ogg","text":"ˈaɪ.sə.leɪt"},"us":{"mp3":"http://dictionary.cambridge.org/media/english/us_pron/i/iso/isola/isolate.mp3","ogg":"http://dictionary.cambridge.org/media/english/us_pron_ogg/i/iso/isola/isolate.ogg","text":"ˈaɪ.sə.leɪt"}},"definitions":[{"definition":"to separate something from other things with which it is connected or mixed: ","examples":["A high wall isolated the house from the rest of the village."]},{"definition":"to keep a person or animal separate from other people or animals by putting them in a different place: ","examples":["He was isolated from all the other prisoners."]},{"definition":"to put a person, country, or organization in a situation where they are seen as being separate : ","examples":["This policy will isolate minority groups and prevent integration."]}]}]