[{"word":"vanadium","type":"noun","pronunc":{"uk":{"mp3":"http://dictionary.cambridge.org/media/english/uk_pron/e/epd/epd29/epd29458.mp3","ogg":"http://dictionary.cambridge.org/media/english/uk_pron_ogg/e/epd/epd29/epd29458.ogg","text":"vəˈneɪ.di.əm"},"us":{"mp3":"http://dictionary.cambridge.org/media/english/us_pron/e/eus/eus28/eus28924.mp3","ogg":"http://dictionary.cambridge.org/media/english/us_pron_ogg/e/eus/eus28/eus28924.ogg","text":"vəˈneɪ.di.əm"}},"definitions":[{"definition":"a chemical element that is a silver-grey metal, used to make steel alloys (= mixtures of metals) and in ceramics (= making objects out of baked clay)"}]}]