[{"word":"varnish","type":"noun","pronunc":{"uk":{"mp3":"http://dictionary.cambridge.org/media/english/uk_pron/u/ukv/ukvar/ukvario003.mp3","ogg":"http://dictionary.cambridge.org/media/english/uk_pron_ogg/u/ukv/ukvar/ukvario003.ogg","text":"ˈvɑː.nɪʃ"},"us":{"mp3":"http://dictionary.cambridge.org/media/english/us_pron/v/var/varni/varnish.mp3","ogg":"http://dictionary.cambridge.org/media/english/us_pron_ogg/v/var/varni/varnish.ogg","text":"ˈvɑːr.nɪʃ"}},"definitions":[{"definition":"a liquid that is painted onto wood or paintings to protect the surface, or the hard shiny surface it produces when it dries: ","examples":["Polyurethane varnish provides a tough, scratch-resistant finish."]}]},{"word":"varnish","type":"verb","pronunc":{"uk":{"mp3":"http://dictionary.cambridge.org/media/english/uk_pron/u/ukv/ukvar/ukvario003.mp3","ogg":"http://dictionary.cambridge.org/media/english/uk_pron_ogg/u/ukv/ukvar/ukvario003.ogg","text":"ˈvɑː.nɪʃ"},"us":{"mp3":"http://dictionary.cambridge.org/media/english/us_pron/v/var/varni/varnish.mp3","ogg":"http://dictionary.cambridge.org/media/english/us_pron_ogg/v/var/varni/varnish.ogg","text":"ˈvɑːr.nɪʃ"}},"definitions":[{"definition":"to put varnish on a surface: ","examples":["They decided to spend the weekend varnishing their boat."]},{"definition":"to use nail varnish"}]}]