[{"word":"vertigo","type":"noun","pronunc":{"uk":{"mp3":"http://dictionary.cambridge.org/media/english/uk_pron/u/ukv/ukver/ukverit030.mp3","ogg":"http://dictionary.cambridge.org/media/english/uk_pron_ogg/u/ukv/ukver/ukverit030.ogg","text":"ˈvɜː.tɪ.ɡəʊ"},"us":{"mp3":"http://dictionary.cambridge.org/media/english/us_pron/v/ver/verti/vertigo.mp3","ogg":"http://dictionary.cambridge.org/media/english/us_pron_ogg/v/ver/verti/vertigo.ogg","text":"ˈvɝː.t̬ə.ɡoʊ"}},"definitions":[{"definition":"a feeling of spinning around and being unable to balance, often caused by looking down from a height: ","examples":["She can't stand heights and has always suffered from vertigo."]}]}]