[{"word":"daintily","type":"adverb","pronunc":{"uk":{"mp3":"http://dictionary.cambridge.org/media/english/uk_pron/u/ukd/ukdag/ukdagoe007.mp3","ogg":"http://dictionary.cambridge.org/media/english/uk_pron_ogg/u/ukd/ukdag/ukdagoe007.ogg","text":"ˈdeɪn.tə"},"us":{"mp3":"http://dictionary.cambridge.org/media/english/us_pron/u/usd/usd__/usd____016.mp3","ogg":"http://dictionary.cambridge.org/media/english/us_pron_ogg/u/usd/usd__/usd____016.ogg","text":"ˈdeɪn.t̬ə"}},"definitions":[{"definition":"in an attractive, careful way, especially used about something small or having small movements: ","examples":["She skipped daintily down the street, holding her father's hand."]}]}]