[{"word":"discussion","type":"noun","pronunc":{"uk":{"mp3":"http://dictionary.cambridge.org/media/english/uk_pron/u/ukd/ukdis/ukdiscr005.mp3","ogg":"http://dictionary.cambridge.org/media/english/uk_pron_ogg/u/ukd/ukdis/ukdiscr005.ogg","text":"dɪˈskʌʃ.ə"},"us":{"mp3":"http://dictionary.cambridge.org/media/english/us_pron/d/dis/discu/discussion.mp3","ogg":"http://dictionary.cambridge.org/media/english/us_pron_ogg/d/dis/discu/discussion.ogg","text":"dɪˈskʌʃ.ə"}},"definitions":[{"definition":"the activity in which people talk about something and tell each other their ideas or opinions: ","examples":["We will hold/have discussions with employee representatives about possible redundancies."]}]}]