[{"word":"disreputable","type":"adjective","pronunc":{"uk":{"mp3":"http://dictionary.cambridge.org/media/english/uk_pron/u/ukd/ukdis/ukdisre002.mp3","ogg":"http://dictionary.cambridge.org/media/english/uk_pron_ogg/u/ukd/ukdis/ukdisre002.ogg","text":"dɪsˈrep.jə.tə.bə"},"us":{"mp3":"http://dictionary.cambridge.org/media/english/us_pron/d/dis/disre/disreputable.mp3","ogg":"http://dictionary.cambridge.org/media/english/us_pron_ogg/d/dis/disre/disreputable.ogg","text":"dɪsˈrep.jə.t̬ə.bə"}},"definitions":[{"definition":"not trusted or respected; thought to have a bad character: ","examples":["Some of the more disreputable newspapers made false claims about her private life."]}]}]