[{"word":"documentary","type":"noun","pronunc":{"uk":{"mp3":"http://dictionary.cambridge.org/media/english/uk_pron/u/ukd/ukdoc/ukdocud003.mp3","ogg":"http://dictionary.cambridge.org/media/english/uk_pron_ogg/u/ukd/ukdoc/ukdocud003.ogg","text":"ˌdɒk.jəˈmen.tə"},"us":{"mp3":"http://dictionary.cambridge.org/media/english/us_pron/e/eus/eus71/eus71353.mp3","ogg":"http://dictionary.cambridge.org/media/english/us_pron_ogg/e/eus/eus71/eus71353.ogg","text":"ˌdɑː.kjəˈmen.t̬ɚ.i"}},"definitions":[{"definition":"a film or television or radio programme that gives facts and information about a subject: ","examples":["The documentary took a fresh look at the life of Darwin."]}]},{"word":"documentary","type":"adjective","pronunc":{"uk":{"mp3":"http://dictionary.cambridge.org/media/english/uk_pron/u/ukd/ukdoc/ukdocud003.mp3","ogg":"http://dictionary.cambridge.org/media/english/uk_pron_ogg/u/ukd/ukdoc/ukdocud003.ogg","text":"ˌdɒk.jəˈmen.tə"},"us":{"mp3":"http://dictionary.cambridge.org/media/english/us_pron/e/eus/eus71/eus71353.mp3","ogg":"http://dictionary.cambridge.org/media/english/us_pron_ogg/e/eus/eus71/eus71353.ogg","text":"ˌdɑː.kjəˈmen.t̬ɚ.i"}},"definitions":[{"definition":"in the form of documents: ","examples":["Human rights campaigners have discovered documentary evidence of torture."]},{"definition":"giving facts and information about a subject in the form of a film or television or radio programme: ","examples":["Most of her movies have a documentary style."]}]}]