[{"word":"tissue","type":"noun","pronunc":{"uk":{"mp3":"http://dictionary.cambridge.org/media/english/uk_pron/u/ukt/uktip/uktippe021.mp3","ogg":"http://dictionary.cambridge.org/media/english/uk_pron_ogg/u/ukt/uktip/uktippe021.ogg","text":"ˈtɪʃ.uː"},"us":{"mp3":"http://dictionary.cambridge.org/media/english/us_pron/t/tis/tissu/tissue.mp3","ogg":"http://dictionary.cambridge.org/media/english/us_pron_ogg/t/tis/tissu/tissue.ogg","text":"ˈtɪʃ.uː"}},"definitions":[{"definition":"a group of connected cells in an animal or plant that are similar to each other, have the same purpose, and form the stated part of the animal or plant: ","examples":["human tissue"]}]}]