[{"word":"trench","type":"noun","pronunc":{"uk":{"mp3":"http://dictionary.cambridge.org/media/english/uk_pron/u/ukt/uktre/uktremu003.mp3","ogg":"http://dictionary.cambridge.org/media/english/uk_pron_ogg/u/ukt/uktre/uktremu003.ogg","text":"trentʃ"},"us":{"mp3":"http://dictionary.cambridge.org/media/english/us_pron/t/tre/trenc/trench.mp3","ogg":"http://dictionary.cambridge.org/media/english/us_pron_ogg/t/tre/trenc/trench.ogg","text":"trentʃ"}},"definitions":[{"definition":"a narrow hole that is dug into the ground: ","examples":["A workman was killed when the sides of the trench he was working in collapsed."]},{"definition":"a deep hole dug by soldiers and used as a place from which they can attack the enemy while being hidden: ","examples":["the trenches of the First World War"]}]}]