[{"word":"racism","type":"noun","pronunc":{"uk":{"mp3":"http://dictionary.cambridge.org/media/english/uk_pron/u/ukr/ukrab/ukrabbi021.mp3","ogg":"http://dictionary.cambridge.org/media/english/uk_pron_ogg/u/ukr/ukrab/ukrabbi021.ogg","text":"ˈreɪ.sɪ.zə"},"us":{"mp3":"http://dictionary.cambridge.org/media/english/us_pron/r/rac/racis/racism.mp3","ogg":"http://dictionary.cambridge.org/media/english/us_pron_ogg/r/rac/racis/racism.ogg","text":"ˈreɪ.sɪ.zə"}},"definitions":[{"definition":"the belief that people's qualities are influenced by their race and that the members of other races are not as good as the members of your own, or the resulting unfair treatment of members of other races: ","examples":["The authorities are taking steps to combat/fight/tackle racism in schools."]}]}]