[{"word":"railway","type":"noun","pronunc":{"uk":{"mp3":"http://dictionary.cambridge.org/media/english/uk_pron/u/ukr/ukraf/ukraffl023.mp3","ogg":"http://dictionary.cambridge.org/media/english/uk_pron_ogg/u/ukr/ukraf/ukraffl023.ogg","text":"ˈreɪl.weɪ"},"us":{"mp3":"http://dictionary.cambridge.org/media/english/us_pron/r/rai/railw/railway_railroad.mp3","ogg":"http://dictionary.cambridge.org/media/english/us_pron_ogg/r/rai/railw/railway_railroad.ogg","text":"ˈreɪl.weɪ"}},"definitions":[{"definition":"the metal tracks on which trains run: ","examples":["We live close to the railway line."]},{"definition":"the system of tracks, stations, trains, etc.: ","examples":["a railway station/timetable/siding"]}]}]