[{"word":"rebuff","type":"verb","pronunc":{"uk":{"mp3":"http://dictionary.cambridge.org/media/english/uk_pron/u/ukr/ukrea/ukreapp029.mp3","ogg":"http://dictionary.cambridge.org/media/english/uk_pron_ogg/u/ukr/ukrea/ukreapp029.ogg","text":"rɪˈbʌf"},"us":{"mp3":"http://dictionary.cambridge.org/media/english/us_pron/r/reb/rebuf/rebuff.mp3","ogg":"http://dictionary.cambridge.org/media/english/us_pron_ogg/r/reb/rebuf/rebuff.ogg","text":"rɪˈbʌf"}},"definitions":[{"definition":"to refuse to accept a helpful suggestion or offer from someone, often by answering in an unfriendly way: ","examples":["She rebuffed all suggestions that she should resign."]}]}]