[{"word":"regulate","type":"verb","pronunc":{"uk":{"mp3":"http://dictionary.cambridge.org/media/english/uk_pron/u/ukr/ukreg/ukregul005.mp3","ogg":"http://dictionary.cambridge.org/media/english/uk_pron_ogg/u/ukr/ukreg/ukregul005.ogg","text":"ˈreɡ.jə.leɪt"},"us":{"mp3":"http://dictionary.cambridge.org/media/english/us_pron/r/reg/regul/regulate.mp3","ogg":"http://dictionary.cambridge.org/media/english/us_pron_ogg/r/reg/regul/regulate.ogg","text":"ˈreɡ.jə.leɪt"}},"definitions":[{"definition":"to control something, especially by making it work in a particular way: ","examples":["You can regulate the temperature in the house by adjusting the thermostat."]}]}]