[{"word":"reverse","type":"verb","pronunc":{"uk":{"mp3":"http://dictionary.cambridge.org/media/english/uk_pron/u/ukr/ukrev/ukrev__027.mp3","ogg":"http://dictionary.cambridge.org/media/english/uk_pron_ogg/u/ukr/ukrev/ukrev__027.ogg","text":"rɪˈvɜːs"},"us":{"mp3":"http://dictionary.cambridge.org/media/english/us_pron/r/rev/rever/reverse.mp3","ogg":"http://dictionary.cambridge.org/media/english/us_pron_ogg/r/rev/rever/reverse.ogg","text":"rɪˈvɝːs"}},"definitions":[{"definition":"to change the direction, order, position, result, etc. of something to its opposite: ","examples":["The new manager hoped to reverse the decline in the company's fortunes."]}]}]