[{"word":"room","type":"noun","pronunc":{"uk":{"mp3":"http://dictionary.cambridge.org/media/english/uk_pron/u/ukr/ukroo/ukrooke003.mp3","ogg":"http://dictionary.cambridge.org/media/english/uk_pron_ogg/u/ukr/ukroo/ukrooke003.ogg","text":"ruːm"},"us":{"mp3":"http://dictionary.cambridge.org/media/english/us_pron/r/roo/room_/room.mp3","ogg":"http://dictionary.cambridge.org/media/english/us_pron_ogg/r/roo/room_/room.ogg","text":"ruːm"}},"definitions":[{"definition":"a part of the inside of a building that is separated from other parts by walls, floor, and ceiling: ","examples":["I like this room - it has plenty of light."]},{"definition":"a bedroom: ","examples":["She's upstairs in her room."]},{"definition":"used as a combining form in the names of particular rooms: ","examples":["a bedroom"]},{"definition":"a set of rented rooms, especially in a college or university"}]},{"word":"room","type":"verb","pronunc":{"uk":{"mp3":"http://dictionary.cambridge.org/media/english/uk_pron/u/ukr/ukroo/ukrooke003.mp3","ogg":"http://dictionary.cambridge.org/media/english/uk_pron_ogg/u/ukr/ukroo/ukrooke003.ogg","text":"ruːm"},"us":{"mp3":"http://dictionary.cambridge.org/media/english/us_pron/r/roo/room_/room.mp3","ogg":"http://dictionary.cambridge.org/media/english/us_pron_ogg/r/roo/room_/room.ogg","text":"ruːm"}},"definitions":[{"definition":"to rent a room from someone, or share a rented room with someone: ","examples":["At college he rooms with this guy from Nebraska."]}]}]