[{"word":"uphill","type":"adjective","pronunc":{"uk":{"mp3":"http://dictionary.cambridge.org/media/english/uk_pron/u/uku/ukunw/ukunwis022.mp3","ogg":"http://dictionary.cambridge.org/media/english/uk_pron_ogg/u/uku/ukunw/ukunwis022.ogg","text":"ˌʌpˈhɪl"},"us":{"mp3":"http://dictionary.cambridge.org/media/english/us_pron/u/usu/usuns/usunsoc029.mp3","ogg":"http://dictionary.cambridge.org/media/english/us_pron_ogg/u/usu/usuns/usunsoc029.ogg","text":"ˌʌpˈhɪl"}},"definitions":[{"definition":"leading to a higher place on a slope: ","examples":["an uphill climb"]},{"definition":"needing a large amount of effort: ","examples":["It'll be an uphill struggle/battle/fight to get the new proposals accepted."]}]}]