[{"word":"caravan","type":"noun","pronunc":{"uk":{"mp3":"http://dictionary.cambridge.org/media/english/uk_pron/u/ukc/ukcar/ukcarap004.mp3","ogg":"http://dictionary.cambridge.org/media/english/uk_pron_ogg/u/ukc/ukcar/ukcarap004.ogg","text":"ˈkær.ə.væn"},"us":{"mp3":"http://dictionary.cambridge.org/media/english/us_pron/c/car/carav/caravan.mp3","ogg":"http://dictionary.cambridge.org/media/english/us_pron_ogg/c/car/carav/caravan.ogg","text":"ˈker.ə.væn"}},"definitions":[{"definition":"a wheeled vehicle for living or travelling in, especially for holidays, that contains beds and cooking equipment and can be pulled by a car"},{"definition":"a painted wooden vehicle that is pulled by a horse and in which people live: ","examples":["a gypsy caravan"]}]}]