[{"word":"compound","type":"noun","pronunc":{"uk":{"mp3":"http://dictionary.cambridge.org/media/english/uk_pron/u/ukc/ukcom/ukcompl019.mp3","ogg":"http://dictionary.cambridge.org/media/english/uk_pron_ogg/u/ukc/ukcom/ukcompl019.ogg","text":"ˈkɒm.paʊnd"},"us":{"mp3":"http://dictionary.cambridge.org/media/english/us_pron/c/com/compo/compound_01_00.mp3","ogg":"http://dictionary.cambridge.org/media/english/us_pron_ogg/c/com/compo/compound_01_00.ogg","text":"ˈkɑːm-"}},"definitions":[{"definition":"a chemical that combines two or more elements: ","examples":["Salt is a compound of sodium and chlorine."]},{"definition":"something consisting of two or more different parts: ","examples":["Then there was his manner, a curious compound of humour and severity."]},{"definition":"a word that combines two or more different words. Often, the meaning of the compound cannot be discovered by knowing the meaning of the different words that form it. Compounds may be written either as one word or as separate words: ","examples":["'Bodyguard' and 'floppy disk' are two examples of compounds."]}]},{"word":"compound","type":"verb","pronunc":{"uk":{"mp3":"http://dictionary.cambridge.org/media/english/uk_pron/u/ukc/ukcom/ukcompl020.mp3","ogg":"http://dictionary.cambridge.org/media/english/uk_pron_ogg/u/ukc/ukcom/ukcompl020.ogg","text":"kəmˈpaʊnd"},"us":{"mp3":"http://dictionary.cambridge.org/media/english/us_pron/e/eus/eus70/eus70926.mp3","ogg":"http://dictionary.cambridge.org/media/english/us_pron_ogg/e/eus/eus70/eus70926.ogg","text":"kəmˈpaʊnd"}},"definitions":[{"definition":"to make a problem or difficult situation worse: ","examples":["Her terror was compounded by the feeling that she was being watched."]}]},{"word":"compound","type":"adjective","pronunc":{"uk":{"mp3":"http://dictionary.cambridge.org/media/english/uk_pron/u/ukc/ukcom/ukcompl019.mp3","ogg":"http://dictionary.cambridge.org/media/english/uk_pron_ogg/u/ukc/ukcom/ukcompl019.ogg","text":"ˈkɒm.paʊnd"},"us":{"mp3":"http://dictionary.cambridge.org/media/english/us_pron/c/com/compo/compound_01_00.mp3","ogg":"http://dictionary.cambridge.org/media/english/us_pron_ogg/c/com/compo/compound_01_00.ogg","text":"ˈkɑːm-"}},"definitions":[{"definition":"consisting of two or more parts"},{"definition":"used to refer to a system of paying interest in which interest is paid both on the original amount of money invested (= given to companies hoping to get more back) or borrowed and on the interest that has collected over a period of time: ","examples":["compound interest"]}]}]