[{"word":"compliance","type":"noun","pronunc":{"uk":{"mp3":"http://dictionary.cambridge.org/media/english/uk_pron/u/ukc/ukcom/ukcompe025.mp3","ogg":"http://dictionary.cambridge.org/media/english/uk_pron_ogg/u/ukc/ukcom/ukcompe025.ogg","text":"kəmˈplaɪ.əns"},"us":{"mp3":"http://dictionary.cambridge.org/media/english/us_pron/c/com/compl/compliance.mp3","ogg":"http://dictionary.cambridge.org/media/english/us_pron_ogg/c/com/compl/compliance.ogg","text":"kəmˈplaɪ.əns"}},"definitions":[{"definition":"the act of obeying an order, rule, or request: ","examples":["It is the job of the inspectors to enforce compliance with the regulations."]},{"definition":"the state of being too willing to do what other people want you to do: ","examples":["It's his compliance that amazes me."]}]}]