[{"word":"fallow","type":"adjective","pronunc":{"uk":{"mp3":"http://dictionary.cambridge.org/media/english/uk_pron/u/ukf/ukfal/ukfalaf020.mp3","ogg":"http://dictionary.cambridge.org/media/english/uk_pron_ogg/u/ukf/ukfal/ukfalaf020.ogg","text":"ˈfæl.əʊ"},"us":{"mp3":"http://dictionary.cambridge.org/media/english/us_pron/u/usf/usfal/usfalli004.mp3","ogg":"http://dictionary.cambridge.org/media/english/us_pron_ogg/u/usf/usfal/usfalli004.ogg","text":"ˈfæl.oʊ"}},"definitions":[{"definition":"Fallow land is not planted with crops, in order to improve the quality of the soil: ","examples":["Farmers are eligible for government support if they let a certain amount of land lie fallow."]}]}]