[{"word":"featherbed","type":"verb","pronunc":{"uk":{"mp3":"http://dictionary.cambridge.org/media/english/uk_pron/u/ukf/ukfea/ukfeast004.mp3","ogg":"http://dictionary.cambridge.org/media/english/uk_pron_ogg/u/ukf/ukfea/ukfeast004.ogg","text":"ˌfeð.əˈbed"},"us":{"mp3":"http://dictionary.cambridge.org/media/english/us_pron/u/usf/usfat/usfatuo016.mp3","ogg":"http://dictionary.cambridge.org/media/english/us_pron_ogg/u/usf/usfat/usfatuo016.ogg","text":"ˌfeð.ɚˈbed"}},"definitions":[{"definition":"to protect someone, especially a group of workers, too much and make things easy for them"},{"definition":"If a government featherbeds an industry, it gives it a lot of help, such as lower taxes, especially so that jobs will not be lost."}]}]