[{"word":"flare","type":"verb","pronunc":{"uk":{"mp3":"http://dictionary.cambridge.org/media/english/uk_pron/u/ukf/ukfla/ukflacc016.mp3","ogg":"http://dictionary.cambridge.org/media/english/uk_pron_ogg/u/ukf/ukfla/ukflacc016.ogg","text":"fleər"},"us":{"mp3":"http://dictionary.cambridge.org/media/english/us_pron/f/fla/flair/flair.mp3","ogg":"http://dictionary.cambridge.org/media/english/us_pron_ogg/f/fla/flair/flair.ogg","text":"fler"}},"definitions":[{"definition":"to burn brightly either for a short time or not regularly: ","examples":["The flame above the oil well flared (up) into the dark sky."]}]},{"word":"flare","type":"noun","pronunc":{"uk":{"mp3":"http://dictionary.cambridge.org/media/english/uk_pron/u/ukf/ukfla/ukflacc016.mp3","ogg":"http://dictionary.cambridge.org/media/english/uk_pron_ogg/u/ukf/ukfla/ukflacc016.ogg","text":"fleər"},"us":{"mp3":"http://dictionary.cambridge.org/media/english/us_pron/f/fla/flair/flair.mp3","ogg":"http://dictionary.cambridge.org/media/english/us_pron_ogg/f/fla/flair/flair.ogg","text":"fler"}},"definitions":[{"definition":"a sudden increase in the brightness of a fire: ","examples":["There was a sudden flare when she threw the petrol onto the fire."]},{"definition":"a very bright light or coloured smoke that can be used as a signal, or a device that produces this: ","examples":["We set off a flare to help guide our rescuers."]}]}]