[{"word":"frontier","type":"noun","pronunc":{"uk":{"mp3":"http://dictionary.cambridge.org/media/english/uk_pron/u/ukf/ukfro/ukfrom_009.mp3","ogg":"http://dictionary.cambridge.org/media/english/uk_pron_ogg/u/ukf/ukfro/ukfrom_009.ogg","text":"ˈfrʌn.tɪər"},"us":{"mp3":"http://dictionary.cambridge.org/media/english/us_pron/f/fro/front/frontier.mp3","ogg":"http://dictionary.cambridge.org/media/english/us_pron_ogg/f/fro/front/frontier.ogg","text":"frʌnˈtɪr"}},"definitions":[{"definition":"a border between two countries: ","examples":["Some of the frontier between Germany and Poland follows the course of the river Oder"]},{"definition":"the western US where settlers began to move to live in the 19th century: ","examples":["The Homestead Act of 1862 gave free land to pioneers who settled the frontier."]}]}]