[{"word":"scroll","type":"noun","pronunc":{"uk":{"mp3":"http://dictionary.cambridge.org/media/english/uk_pron/u/uks/ukscr/ukscrib011.mp3","ogg":"http://dictionary.cambridge.org/media/english/uk_pron_ogg/u/uks/ukscr/ukscrib011.ogg","text":"skrəʊl"},"us":{"mp3":"http://dictionary.cambridge.org/media/english/us_pron/s/scr/scrol/scroll.mp3","ogg":"http://dictionary.cambridge.org/media/english/us_pron_ogg/s/scr/scrol/scroll.ogg","text":"skroʊl"}},"definitions":[{"definition":"a long roll of paper or similar material with usually official writing on it: ","examples":["The ancient Egyptians stored information on scrolls."]},{"definition":"a decoration that looks like a roll of paper: ","examples":["The tops of the marble pillars were decorated with scrolls."]}]},{"word":"scroll","type":"verb","pronunc":{"uk":{"mp3":"http://dictionary.cambridge.org/media/english/uk_pron/u/uks/ukscr/ukscrib011.mp3","ogg":"http://dictionary.cambridge.org/media/english/uk_pron_ogg/u/uks/ukscr/ukscrib011.ogg","text":"skrəʊl"},"us":{"mp3":"http://dictionary.cambridge.org/media/english/us_pron/s/scr/scrol/scroll.mp3","ogg":"http://dictionary.cambridge.org/media/english/us_pron_ogg/s/scr/scrol/scroll.ogg","text":"skroʊl"}},"definitions":[{"definition":"to move text or other information on a computer screen in order to see a different part of it: ","examples":["Scroll to the end of the document."]}]}]