[{"word":"sensation","type":"noun","pronunc":{"uk":{"mp3":"http://dictionary.cambridge.org/media/english/uk_pron/u/uks/uksen/uksen__014.mp3","ogg":"http://dictionary.cambridge.org/media/english/uk_pron_ogg/u/uks/uksen/uksen__014.ogg","text":"senˈseɪ.ʃə"},"us":{"mp3":"http://dictionary.cambridge.org/media/english/us_pron/s/sen/sensa/sensation.mp3","ogg":"http://dictionary.cambridge.org/media/english/us_pron_ogg/s/sen/sensa/sensation.ogg","text":"senˈseɪ.ʃə"}},"definitions":[{"definition":"the ability to feel something physically, especially by touching, or a physical feeling that results from this ability: ","examples":["a burning sensation"]},{"definition":"a general feeling caused by something that happens to you, especially a feeling that you cannot describe exactly: ","examples":["[ + (that) ] I had the odd sensation (that) someone was following me."]}]}]