[{"word":"sermonize","type":"verb","pronunc":{"uk":{"mp3":"http://dictionary.cambridge.org/media/english/uk_pron/u/uks/ukser/ukseren018.mp3","ogg":"http://dictionary.cambridge.org/media/english/uk_pron_ogg/u/uks/ukser/ukseren018.ogg","text":"ˈsɜː.mə.naɪz"},"us":{"mp3":"http://dictionary.cambridge.org/media/english/us_pron/e/eus/eus74/eus74172.mp3","ogg":"http://dictionary.cambridge.org/media/english/us_pron_ogg/e/eus/eus74/eus74172.ogg","text":"ˈsɝː.mə.naɪz"}},"definitions":[{"definition":"to give a long talk to people, telling them how they should behave in order to be better people: ","examples":["My grandmother's all right until she starts sermonizing and then she's unbearable."]}]}]