[{"word":"spank","type":"verb","pronunc":{"uk":{"mp3":"http://dictionary.cambridge.org/media/english/uk_pron/u/uks/ukspa/ukspaci018.mp3","ogg":"http://dictionary.cambridge.org/media/english/uk_pron_ogg/u/uks/ukspa/ukspaci018.ogg","text":"spæŋk"},"us":{"mp3":"http://dictionary.cambridge.org/media/english/us_pron/s/spa/spank/spank.mp3","ogg":"http://dictionary.cambridge.org/media/english/us_pron_ogg/s/spa/spank/spank.ogg","text":"spæŋk"}},"definitions":[{"definition":"to hit a child with the hand, usually several times on the bottom as a punishment"},{"definition":"to hit an adult on the bottom in order to get or give sexual pleasure"}]}]