[{"word":"swerve","type":"verb","pronunc":{"uk":{"mp3":"http://dictionary.cambridge.org/media/english/uk_pron/u/uks/ukswe/uksweet009.mp3","ogg":"http://dictionary.cambridge.org/media/english/uk_pron_ogg/u/uks/ukswe/uksweet009.ogg","text":"swɜːv"},"us":{"mp3":"http://dictionary.cambridge.org/media/english/us_pron/s/swe/swerv/swerve.mp3","ogg":"http://dictionary.cambridge.org/media/english/us_pron_ogg/s/swe/swerv/swerve.ogg","text":"swɝːv"}},"definitions":[{"definition":"to change direction, especially suddenly: ","examples":["The bus driver swerved to avoid hitting a cyclist."]},{"definition":"If you do not swerve from a principle or certain actions, you continue to think or act as you did in the beginning: ","examples":["She is one of those rare politicians whom one can trust not to swerve from policy and principle."]}]}]