[{"word":"symmetry","type":"noun","pronunc":{"uk":{"mp3":"http://dictionary.cambridge.org/media/english/uk_pron/u/uks/uksyb/uksybar026.mp3","ogg":"http://dictionary.cambridge.org/media/english/uk_pron_ogg/u/uks/uksyb/uksybar026.ogg","text":"ˈsɪm.ə.tri"},"us":{"mp3":"http://dictionary.cambridge.org/media/english/us_pron/s/sym/symme/symmetry.mp3","ogg":"http://dictionary.cambridge.org/media/english/us_pron_ogg/s/sym/symme/symmetry.ogg","text":"ˈsɪm.ə.tri"}},"definitions":[{"definition":"the quality of having parts that match each other, especially in a way that is attractive, or similarity of shape or contents: ","examples":["The design of the house had a pleasing symmetry, its oblong shape being picked up in its elongated windows."]},{"definition":"in mathematics, the quality of having two parts that match exactly, either when one half is like an image of the other half in a mirror, or when one part can take the place of another if it is turned 90° or 180°"}]}]