[{"word":"syrup","type":"noun","pronunc":{"uk":{"mp3":"http://dictionary.cambridge.org/media/english/uk_pron/u/uks/uksyn/uksynta013.mp3","ogg":"http://dictionary.cambridge.org/media/english/uk_pron_ogg/u/uks/uksyn/uksynta013.ogg","text":"ˈsɪr.əp"},"us":{"mp3":"http://dictionary.cambridge.org/media/english/us_pron/s/syr/syrup/syrup.mp3","ogg":"http://dictionary.cambridge.org/media/english/us_pron_ogg/s/syr/syrup/syrup.ogg","text":"ˈsɪr.əp"}},"definitions":[{"definition":"a very sweet, thick liquid: ","examples":["Make a syrup by boiling 100 g sugar in 300 ml water."]},{"definition":"a type of sweet liquid medicine: ","examples":["cough syrup"]}]}]