[{"word":"morass","type":"noun","pronunc":{"uk":{"mp3":"http://dictionary.cambridge.org/media/english/uk_pron/u/ukm/ukmoo/ukmooni024.mp3","ogg":"http://dictionary.cambridge.org/media/english/uk_pron_ogg/u/ukm/ukmoo/ukmooni024.ogg","text":"məˈræs"},"us":{"mp3":"http://dictionary.cambridge.org/media/english/us_pron/m/mor/moras/morass.mp3","ogg":"http://dictionary.cambridge.org/media/english/us_pron_ogg/m/mor/moras/morass.ogg","text":"məˈræs"}},"definitions":[{"definition":"something that is extremely complicated and difficult to deal with and makes any progress almost impossible: ","examples":["The morass of rules and regulations is delaying the start of the project."]}]}]